{
    "focalDocName": "ISO27001",
    "focalDocVersion": "2013",
    "focalDocIdentifier": "ISO27001:2013 Annex A Controls (without Control Citation) & Mandatory Controls",
    "focalDocElements": [
      {
        "element": "A.5",
        "title": "Security Policy",
        "type": "Function",
        "description": "",
        "childElements": [
          {
            "element": "A.5.1",
            "title": "Information Security Policies",
            "type": "Category",
            "description": "To provide management direction and support for information security in accordance with business requirements and relevant laws and regulations.",
            "childElements": [
              {
                "element": "A.5.1.1",
                "title": "Policies for information security",
                "type": "Subcategory",
                "description": "",
                "references": [
                  {
                    "documentTitle": [],
                    "location": [],
                    "mandatory": [],
                    "2022-mapping": ["5.1"]
                  }
                ]
              },
              {
                "element": "A.5.1.2",
                "title": "Review of the policies for information security",
                "type": "Subcategory",
                "description": "",
                 "references": [
                  {
                    "documentTitle": [],
                    "location": [],
                    "mandatory": [],
                    "2022-mapping": ["5.1"]
                  }
                ]
              }
            ]
          }
        ]
      },
    {
      "element": "A.6",
      "title": "Organization of information security",
      "type": "Function",
      "description": "",
      "childElements": [
        {
          "element": "A.6.1",
          "title": "Internal Organisation",
          "type": "Category",
          "description": "To establish a management framework to initiate and control the implementation and operation of information security within the organization.",
          "childElements": [
            {
              "element": "A.6.1.1",
              "title": "Information security roles and responsibilities",
              "type": "Subcategory",
              "description": "",
               "references": [
                  {
                    "documentTitle": [],
                    "location": [],
                    "mandatory": [],
                    "2022-mapping": ["5.2"]
                  }
                ]
            },
            {
              "element": "A.6.1.2",
              "title": "Review of the policies for information security",
              "type": "Subcategory",
              "description": "",
               "references": [
                  {
                    "documentTitle": [],
                    "location": [],
                    "mandatory": [],
                    "2022-mapping": ["5.3"]
                  }
                ]
            },
            {
              "element": "A.6.1.3",
              "title": "Contact with authorities",
              "type": "Subcategory",
              "description": "",
               "references": [
                  {
                    "documentTitle": [],
                    "location": [],
                    "mandatory": [],
                    "2022-mapping": ["5.5"]
                  }
                ]
            },
            {
              "element": "A.6.1.4",
              "title": "Contact with special interest groups",
              "type": "Subcategory",
              "description": "",
               "references": [
                  {
                    "documentTitle": [],
                    "location": [],
                    "mandatory": [],
                    "2022-mapping": ["5.6"]
                  }
                ]
            },
            {
              "element": "A.6.1.5",
              "title": "Information security in project management",
              "type": "Subcategory",
              "description": "",
               "references": [
                  {
                    "documentTitle": [],
                    "location": [],
                    "mandatory": [],
                    "2022-mapping": ["5.8"]
                  }
                ]
            }
          ]
        },
        {
          "element": "A.6.2",
          "title": "Mobile devices and teleworking",
          "type": "Category",
          "description": "To ensure the security of teleworking and use of mobile devices.",
          "childElements": [
            {
              "element": "A.6.2.1",
              "title": "Mobile device policy",
              "type": "Subcategory",
              "description": "",
               "references": [
                  {
                    "documentTitle": [],
                    "location": [],
                    "mandatory": [],
                    "2022-mapping": ["8.1"]
                  }
                ]
            },
            {
              "element": "A.6.2.2",
              "title": "Teleworking",
              "type": "Subcategory",
              "description": "",
               "references": [
                  {
                    "documentTitle": [],
                    "location": [],
                    "mandatory": [],
                    "2022-mapping": ["6.7"]
                  }
                ]
            }
          ]
        }
      ]
    },
      {
        "element": "A.7",
        "title": "Human resource security",
        "type": "Function",
        "description": "",
        "childElements": [
          {
            "element": "A.7.1",
            "title": "Prior to employment",
            "type": "Category",
            "description": "To ensure that employees and contractors understand their responsibilities and are suitable for the roles for which they are considered.",
            "childElements": [
              {
                "element": "A.7.1.1",
                "title": "Screening",
                "type": "Subcategory",
                "description": "",
                 "references": [
                  {
                    "documentTitle": [],
                    "location": [],
                    "mandatory": [],
                    "2022-mapping": ["6.1"]
                  }
                ]
              },
              {
                "element": "A.7.1.2",
                "title": "Terms and condition of employment",
                "type": "Subcategory",
                "description": "",
                "references": [
                  {
                  "documentTitle": ["Definition of security roles and responsibilities"],
                  "location": [],
                  "2022-mapping": ["6.2"]
                  }
                ]
              }
            ]
          },
          {
            "element": "A.7.2",
            "title": "During employment",
            "type": "Category",
            "description": "To ensure that employees and contractors are aware of and fulfil their information security responsibilities.",
            "childElements": [
              {
                "element": "A.7.2.1",
                "title": "Management responsibilities",
                "type": "Subcategory",
                "description": "",
                 "references": [
                  {
                    "documentTitle": [],
                    "location": [],
                    "mandatory": [],
                    "2022-mapping": ["5.4"]
                  }
                ]
              },
              {
                "element": "A.7.2.2",
                "title": "Information security awareness, education and training",
                "type": "Subcategory",
                "description": "",
                 "references": [
                  {
                    "documentTitle": [],
                    "location": [],
                    "mandatory": [],
                    "2022-mapping": ["6.3"]
                  }
                ]
              },
              {
                "element": "A.7.2.3",
                "title": "Disciplinary process",
                "type": "Subcategory",
                "description": "" ,
                 "references": [
                  {
                    "documentTitle": [],
                    "location": [],
                    "mandatory": [],
                    "2022-mapping": ["6.4"]
                  }
                ]
              }
            ]
          },
          {
            "element": "A.7.3",
            "title": "Termination and change of employment",
            "type": "Category",
            "description": "To protect the organization's interests as part of the process of changing or terminatingemployment.",
            "childElements": [
              {
                "element": "A.7.3.1",
                "title": "Termination or change of employment responsibilities",
                "type": "Subcategory",
                "description": "",
                 "references": [
                  {
                    "documentTitle": [],
                    "location": [],
                    "mandatory": [],
                    "2022-mapping": ["6.5"]
                  }
                ]
              }
            ]
          }
        ]
      },
      {
        "element": "A.8",
        "title": "Asset management",
        "type": "Function",
        "description": "",
        "childElements": [
          {
            "element": "A.8.1",
            "title": "Responsibility for assets",
            "type": "Category",
            "description": "To identify organizational assets and define appropriate protection responsibilities.",
            "childElements": [
              {
                "element": "A.8.1.1",
                "title": "Inventory of assets",
                "type": "Subcategory",
                "description": "",
                "references": [
                  {
                    "documentTitle": ["An inventory of assets"],
                    "location": [],
                    "mandatory": ["Y"],
                    "2022-mapping": ["5.9"]
                  }
                ]
              },
              {
                "element": "A.8.1.2",
                "title": "Ownership of assets",
                "type": "Subcategory",
                "description": "",
                 "references": [
                  {
                    "documentTitle": [],
                    "location": [],
                    "mandatory": [],
                    "2022-mapping": ["5.9"]
                  }
                ]
              },
              {
                "element": "A.8.1.3",
                "title": "Acceptable use of assets",
                "type": "Subcategory",
                "description": "",
                "references": [
                  {
                    "documentTitle": ["Rules for the acceptable use of assets"],
                    "location": [],
                    "mandatory": ["Y"],
                    "2022-mapping": ["5.1"]
                  }
                ]
              },
              {
                "element": "A.8.1.4",
                "title": "Return of assets",
                "type": "Subcategory",
                "description": "",
                 "references": [
                  {
                    "documentTitle": [],
                    "location": [],
                    "mandatory": [],
                    "2022-mapping": ["5.11"]
                  }
                ]
              }
            ]
          },
          {
            "element": "A.8.2",
            "title": "Information classification",
            "type": "Category",
            "description": "To ensure that information receives an appropriate level of protection in accordance with its importance to the organization.",
            "childElements": [
              {
                "element": "A.8.2.1",
                "title": "Classification of information",
                "type": "Subcategory",
                "description": "",
                "references": [
                  {
                    "documentTitle": ["Information classification scheme"],
                    "location": [],
                    "mandatory": ["Y"],
                    "2022-mapping": ["5.12"]
                  }
                ]
              },
              {
                "element": "A.8.2.2",
                "title": "Labelling of information",
                "type": "Subcategory",
                "description": "",
                 "references": [
                  {
                    "documentTitle": [],
                    "location": [],
                    "mandatory": [],
                    "2022-mapping": ["5.13"]
                  }
                ]
              },
              {
                "element": "A.8.2.3",
                "title": "Handling of assets",
                "type": "Subcategory",
                "description": "",
                 "references": [
                  {
                    "documentTitle": [],
                    "location": [],
                    "mandatory": [],
                    "2022-mapping": ["5.10"]
                  }
                ]
              }
            ]
          },
          {
            "element": "A.8.3",
            "title": "Media handling",
            "type": "Category",
            "description": "To prevent unauthorized disclosure, modification, removal or destruction of information stored on media.",
            "childElements": [
              {
                "element": "A.8.3.1",
                "title": "Management of removable media",
                "type": "Subcategory",
                "description": "",
                 "references": [
                  {
                    "documentTitle": [],
                    "location": [],
                    "mandatory": [],
                    "2022-mapping": ["7.10"]
                  }
                ]
              },
              {
                "element": "A.8.3.2",
                "title": "Disposal of media",
                "type": "Subcategory",
                "description": "",
                 "references": [
                  {
                    "documentTitle": [],
                    "location": [],
                    "mandatory": [],
                    "2022-mapping": ["7.10"]
                  }
                ]
              },
              {
                "element": "A.8.3.3",
                "title": "Physical media transfer",
                "type": "Subcategory",
                "description": "",
                 "references": [
                  {
                    "documentTitle": [],
                    "location": [],
                    "mandatory": [],
                    "2022-mapping": ["7.10"]
                  }
                ]
              }
            ]
          }
        ]
      },
      {
          "element": "A.9",
          "title": "Access control",
          "type": "Function",
          "description": "",
          "childElements": [
            {
              "element": "A.9.1",
              "title": "Business requirements of access control",
              "type": "Category",
              "description": "To limit access to information and information processing facilities.",
              "childElements": [
                {
                  "element": "A.9.1.1",
                  "title": "Access control policy",
                  "type": "Subcategory",
                  "description": "",
                   "references": [
                    {
                      "documentTitle": ["Access control policy"],
                      "location": [],
                      "mandatory": ["Y"],
                      "2022-mapping": ["5.15"]
                    }
                ]
                },
                {
                  "element": "A.9.1.2",
                  "title": "Access to network and network services",
                  "type": "Subcategory",
                  "description": "",
                   "references": [
                  {
                    "documentTitle": [],
                    "location": [],
                    "mandatory": [],
                    "2022-mapping": ["5.15"]
                  }
                ]
                }
              ]
            },
            {
              "element": "A.9.2",
              "title": "User access management",
              "type": "Category",
              "description": "To ensure authorized user access and to prevent unauthorized access to systems and services.",
              "childElements": [
                {
                  "element": "A.9.2.1",
                  "title": "User registration and de-registration",
                  "type": "Subcategory",
                  "description": "",
                   "references": [
                  {
                    "documentTitle": [],
                    "location": [],
                    "mandatory": [],
                    "2022-mapping": ["5.16"]
                  }
                ]
                },
                {
                  "element": "A.9.2.2",
                  "title": "User access provisioning",
                  "type": "Subcategory",
                  "description": "",
                   "references": [
                  {
                    "documentTitle": [],
                    "location": [],
                    "mandatory": [],
                    "2022-mapping": ["5.18"]
                  }
                ]
                },
                {
                  "element": "A.9.2.3",
                  "title": "Management of privileged access rights",
                  "type": "Subcategory",
                  "description": "",
                   "references": [
                  {
                    "documentTitle": [],
                    "location": [],
                    "mandatory": [],
                    "2022-mapping": ["8.2"]
                  }
                ]
                },
                {
                  "element": "A.9.2.4",
                  "title": "Management of secret authentication information of users",
                  "type": "Subcategory",
                  "description": "",
                   "references": [
                  {
                    "documentTitle": [],
                    "location": [],
                    "mandatory": [],
                    "2022-mapping": ["5.17"]
                  }
                ]
                },
                {
                  "element": "A.9.2.5",
                  "title": "Review of user access rights",
                  "type": "Subcategory",
                  "description": "",
                   "references": [
                  {
                    "documentTitle": [],
                    "location": [],
                    "mandatory": [],
                    "2022-mapping": ["5.18"]
                  }
                ]
                },
                {
                  "element": "A.9.2.6",
                  "title": "Removal or adjustment of access rights",
                  "type": "Subcategory",
                  "description": "",
                   "references": [
                  {
                    "documentTitle": [],
                    "location": [],
                    "mandatory": [],
                    "2022-mapping": ["5.18"]
                  }
                ]
                }
              ]
            },{
                "element": "A.9.3",
                "title": "User responsibilities",
                "type": "Category",
                "description": "To make users accountable for safeguarding their authentication information.",
                "childElements": [
                  {
                    "element": "A.9.3.1",
                    "title": "Use of secret authentication information",
                    "type": "Subcategory",
                    "description": "",
                     "references": [
                  {
                    "documentTitle": [],
                    "location": [],
                    "mandatory": [],
                    "2022-mapping": ["5.17"]
                  }
                ]
                  }
                ]
            },{
              "element": "A.9.4",
              "title": "System and application access control",
              "type": "Category",
              "description": "To prevent unauthorized access to systems and applications.",
              "childElements": [
                {
                  "element": "A.9.4.1",
                  "title": "Information access restriction",
                  "type": "Subcategory",
                  "description": "",
                   "references": [
                  {
                    "documentTitle": [],
                    "location": [],
                    "mandatory": [],
                    "2022-mapping": ["8.3"]
                  }
                ]
                },
                {
                  "element": "A.9.4.2",
                  "title": "Secure log-on procedures",
                  "type": "Subcategory",
                  "description": "",
                   "references": [
                  {
                    "documentTitle": [],
                    "location": [],
                    "mandatory": [],
                    "2022-mapping": ["8.5"]
                  }
                ]
                },
                {
                  "element": "A.9.4.3",
                  "title": "Password management system",
                  "type": "Subcategory",
                  "description": "",
                   "references": [
                  {
                    "documentTitle": [],
                    "location": [],
                    "mandatory": [],
                    "2022-mapping": ["5.17"]
                  }
                ]
                },
                {
                  "element": "A.9.4.4",
                  "title": "Use of privileged utility programs",
                  "type": "Subcategory",
                  "description": "",
                   "references": [
                  {
                    "documentTitle": [],
                    "location": [],
                    "mandatory": [],
                    "2022-mapping": ["8.18"]
                  }
                ]
                },
                {
                  "element": "A.9.4.5",
                  "title": "Access control to program source code",
                  "type": "Subcategory",
                  "description": "",
                   "references": [
                  {
                    "documentTitle": [],
                    "location": [],
                    "mandatory": [],
                    "2022-mapping": ["8.4"]
                  }
                ]
                }
              ]
            }
          ]
      },{
        "element": "A.10",
        "title": "Cryptography",
        "type": "Function",
        "description": "",
        "childElements": [
          {
            "element": "A.10.1",
            "title": "Cryptographic controls",
            "type": "Category",
            "description": "To ensure proper and effective use of cryptography to protect the confidentiality, authenticity and/or integrity of information.",
            "childElements": [
              {
                "element": "A.10.1.1",
                "title": "Policy on the use of cryptographic controls",
                "type": "Subcategory",
                "description": "",
                 "references": [
                  {
                    "documentTitle": [],
                    "location": [],
                    "mandatory": [],
                    "2022-mapping": ["8.24"]
                  }
                ]
              },
              {
                "element": "A.10.1.2",
                "title": "Key management",
                "type": "Subcategory",
                "description": "",
                 "references": [
                  {
                    "documentTitle": [],
                    "location": [],
                    "mandatory": [],
                    "2022-mapping": ["8.24"]
                  }
                ]
              }
            ]
          }
        ]
      },{
        "element": "A.11",
        "title": "Physical and environmental security",
        "type": "Function",
        "description": "",
        "childElements": [
          {
            "element": "A.11.1",
            "title": "Secure areas",
            "type": "Category",
            "description": "To prevent unauthorized physical access, damage and interference to the organization's information and information processing facilities.",
            "childElements": [
              {
                "element": "A.11.1.1",
                "title": "Physical security perimeter",
                "type": "Subcategory",
                "description": "",
                 "references": [
                  {
                    "documentTitle": [],
                    "location": [],
                    "mandatory": [],
                    "2022-mapping": ["7.1"]
                  }
                ]
              },
              {
                "element": "A.11.1.2",
                "title": "Physical entry controls",
                "type": "Subcategory",
                "description": "",
                 "references": [
                  {
                    "documentTitle": [],
                    "location": [],
                    "mandatory": [],
                    "2022-mapping": ["7.2"]
                  }
                ]
              },
              {
                "element": "A.11.1.3",
                "title": "Securing offices, rooms and facilities",
                "type": "Subcategory",
                "description": "",
                 "references": [
                  {
                    "documentTitle": [],
                    "location": [],
                    "mandatory": [],
                    "2022-mapping": ["7.3"]
                  }
                ]
              },
              {
                "element": "A.11.1.4",
                "title": "Protecting against external and environmental threats",
                "type": "Subcategory",
                "description": "",
                 "references": [
                  {
                    "documentTitle": [],
                    "location": [],
                    "mandatory": [],
                    "2022-mapping": ["7.5"]
                  }
                ]
              },
              {
                "element": "A.11.1.5",
                "title": "Working in secure areas",
                "type": "Subcategory",
                "description": "",
                 "references": [
                  {
                    "documentTitle": [],
                    "location": [],
                    "mandatory": [],
                    "2022-mapping": ["7.6"]
                  }
                ]
              },
              {
                "element": "A.11.1.6",
                "title": "Delivery and loading areas",
                "type": "Subcategory",
                "description": "",
                 "references": [
                  {
                    "documentTitle": [],
                    "location": [],
                    "mandatory": [],
                    "2022-mapping": ["7.1"]
                  }
                ]
              }
            ]
          },{
              "element": "A.11.2",
              "title": "Equipment",
              "type": "Category",
              "description": "To prevent loss, damage, theft or compromise of assets and interruption to the organization’s operations.",
              "childElements": [
                {
                  "element": "A.11.2.1",
                  "title": "Siting and protection of equipment ",
                  "type": "Subcategory",
                  "description": "",
                   "references": [
                  {
                    "documentTitle": [],
                    "location": [],
                    "mandatory": [],
                    "2022-mapping": ["7.8"]
                  }
                ]
                },
                {
                  "element": "A.11.2.2",
                  "title": "Supporting utilities",
                  "type": "Subcategory",
                  "description": "",
                   "references": [
                  {
                    "documentTitle": [],
                    "location": [],
                    "mandatory": [],
                    "2022-mapping": ["7.11"]
                  }
                ]
                },
                {
                  "element": "A.11.2.3",
                  "title": "Cabling security",
                  "type": "Subcategory",
                  "description": "",
                   "references": [
                  {
                    "documentTitle": [],
                    "location": [],
                    "mandatory": [],
                    "2022-mapping": ["7.12"]
                  }
                ]
                },
                {
                  "element": "A.11.2.4",
                  "title": "Equipment maintenance",
                  "type": "Subcategory",
                  "description": "",
                   "references": [
                  {
                    "documentTitle": [],
                    "location": [],
                    "mandatory": [],
                    "2022-mapping": ["7.13"]
                  }
                ]
                },
                {
                  "element": "A.11.2.5",
                  "title": "Removal of assets",
                  "type": "Subcategory",
                  "description": "",
                   "references": [
                  {
                    "documentTitle": [],
                    "location": [],
                    "mandatory": [],
                    "2022-mapping": ["7.10"]
                  }
                ]
                },
                {
                  "element": "A.11.2.6",
                  "title": "Security of equipment and assets off-premises",
                  "type": "Subcategory",
                  "description": "",
                   "references": [
                  {
                    "documentTitle": [],
                    "location": [],
                    "mandatory": [],
                    "2022-mapping": ["7.9"]
                  }
                ]
                },
                {
                  "element": "A.11.2.7",
                  "title": "Secure disposal or reuse of equipment",
                  "type": "Subcategory",
                  "description": "",
                   "references": [
                  {
                    "documentTitle": [],
                    "location": [],
                    "mandatory": [],
                    "2022-mapping": ["7.14"]
                  }
                ]
                },
                {
                  "element": "A.11.2.8",
                  "title": "Unattended user equipment",
                  "type": "Subcategory",
                  "description": "",
                  "references": [
                 {
                    "documentTitle": [],
                    "location": [],
                    "mandatory": [],
                    "2022-mapping": ["8.1"]
                  }
               ]
                },
                {
                  "element": "A.11.2.9",
                  "title": "Clear desk and clear screen policy",
                  "type": "Subcategory",
                  "description": "",
                  "references": [
                 {
                    "documentTitle": [],
                    "location": [],
                    "mandatory": [],
                    "2022-mapping": ["7.7"]
                  }
               ]
                }
              ]
          }
        ]
      },{
        "element": "A.12",
        "title": "Operations security",
        "type": "Function",
        "description": "",
        "childElements": [
          {
            "element": "A.12.1",
            "title": "Operational procedures and responsibilities",
            "type": "Category",
            "description": "To ensure correct and secure operations of information processing facilities.",
            "childElements": [
              {
                "element": "A.12.1.1",
                "title": "Documented operating procedures",
                "type": "Subcategory",
                "description": "",
                "references": [
               {
                 "documentTitle": ["Operating procedures for IT management"],
                 "location": [],
                 "mandatory": ["Y"],
                 "2022-mapping": ["5.37"]
               }
             ]
              },
              {
                "element": "A.12.1.2",
                "title": "Change management",
                "type": "Subcategory",
                "description": "",
                "references": [
               {
                 "documentTitle": [],
                 "location": [],
                 "mandatory": [],
                 "2022-mapping": ["8.32"]
               }
             ]
              },
              {
                "element": "A.12.1.3",
                "title": "Capacity management",
                "type": "Subcategory",
                "description": "",
                "references": [
               {
                 "documentTitle": [],
                 "location": [],
                 "mandatory": [],
                 "2022-mapping": ["8.6"]
               }
             ]
              },
              {
                "element": "A.12.1.4",
                "title": "Separation of development, testing and operational environments",
                "type": "Subcategory",
                "description": "",
                "references": [
               {
                 "documentTitle": [],
                 "location": [],
                 "mandatory": [],
                 "2022-mapping": ["8.31"]
               }
             ]
              }
            ]
          },{
            "element": "A.12.2",
            "title": "Protection from malware",
            "type": "Category",
            "description": "To ensure that information and information processing facilities are protected against malware.",
            "childElements": [
              {
                "element": "A.12.2.1",
                "title": "Controls against malware",
                "type": "Subcategory",
                "description": "",
                "references": [
               {
                 "documentTitle": [],
                 "location": [],
                 "mandatory": [],
                 "2022-mapping": ["8.7"]
               }
             ]
              }
            ]
          },{
            "element": "A.12.3",
            "title": "Backup",
            "type": "Category",
            "description": "To protect against loss of data.",
            "childElements": [
              {
                "element": "A.12.3.1",
                "title": "Information backup",
                "type": "Subcategory",
                "description": "",
                "references": [
               {
                 "documentTitle": [],
                 "location": [],
                 "mandatory": [],
                 "2022-mapping": ["8.13"]
               }
             ]
              }
            ]
          },{
            "element": "A.12.4",
            "title": "Logging and monitoring",
            "type": "Category",
            "description": "To record events and generate evidence.",
            "childElements": [
              {
                "element": "A.12.4.1",
                "title": "Event logging",
                "type": "Subcategory",
                "description": "",
                "references": [
                  {
                    "documentTitle": ["Logs of user activities, exceptions, and security events"],
                    "location": [],
                    "mandatory": ["Y"],
                    "2022-mapping": ["8.15"]
                  }
             ]
              },
              {
                "element": "A.12.4.2",
                "title": "Protection of log information",
                "type": "Subcategory",
                "description": "",
                "references": [
               {
                 "documentTitle": [],
                 "location": [],
                 "mandatory": [],
                 "2022-mapping": ["8.15"]
               }
             ]
              },
              {
                "element": "A.12.4.3",
                "title": "Administrator and operator logs",
                "type": "Subcategory",
                "description": "",
                "references": [
               {
                 "documentTitle": ["Logs of user activities, exceptions, and security events"],
                 "location": [],
                 "mandatory": ["Y"],
                 "2022-mapping": ["8.15"]
               }
             ]
              },
              {
                "element": "A.12.4.4",
                "title": "Clock synchronisation",
                "type": "Subcategory",
                "description": "",
                "references": [
               {
                 "documentTitle": [],
                 "location": [],
                 "mandatory": [],
                 "2022-mapping": ["8.17"]
               }
             ]
              }
            ]
          },{
            "element": "A.12.5",
            "title": "Control of operational software",
            "type": "Category",
            "description": "To ensure the integrity of operational systems.",
            "childElements": [
              {
                "element": "A.12.5.1",
                "title": "Installation of software on operational systems",
                "type": "Subcategory",
                "description": "",
                "references": [
               {
                 "documentTitle": [],
                 "location": [],
                 "mandatory": [],
                 "2022-mapping": ["8.19"]
               }
             ]
              }
            ]
          },{
            "element": "A.12.6",
            "title": "Technical vulnerability management",
            "type": "Category",
            "description": "To prevent exploitation of technical vulnerabilities",
            "childElements": [
              {
                "element": "A.12.6.1",
                "title": "Management of technical vulnerabilities",
                "type": "Subcategory",
                "description": "",
                "references": [
               {
                 "documentTitle": [],
                 "location": [],
                 "mandatory": [],
                 "2022-mapping": ["8.8"]
               }
             ]
              },
              {
                "element": "A.12.6.2",
                "title": "Restrictions on software installation",
                "type": "Subcategory",
                "description": "",
                "references": [
               {
                 "documentTitle": [],
                 "location": [],
                 "mandatory": [],
                 "2022-mapping": ["8.19"]
               }
             ]
              }
            ]
          },{
            "element": "A.12.7",
            "title": "Information systems audit considerations",
            "type": "Category",
            "description": "To minimise the impact of audit activities on operational systems.",
            "childElements": [
              {
                "element": "A.12.7.1",
                "title": "Information systems audit controls",
                "type": "Subcategory",
                "description": "",
                "references": [
               {
                 "documentTitle": [],
                 "location": [],
                 "mandatory": [],
                 "2022-mapping": ["8.34"]
               }
             ]
              }
            ]
          }
        ]
      },{
        "element": "A.13",
        "title": "Communications security",
        "type": "Function",
        "description": "",
        "childElements": [
          {
            "element": "A.13.1",
            "title": "Network security management",
            "type": "Category",
            "description": "To ensure the protection of information in networks and its supporting information processing facilities.",
            "childElements": [
              {
                "element": "A.13.1.1",
                "title": "Network controls",
                "type": "Subcategory",
                "description": "",
                "references": [
               {
                 "documentTitle": [],
                 "location": [],
                 "mandatory": [],
                 "2022-mapping": ["8.20"]
               }
             ]
              },
              {
                "element": "A.13.1.2",
                "title": "Security of network services",
                "type": "Subcategory",
                "description": "",
                "references": [
               {
                 "documentTitle": [],
                 "location": [],
                 "mandatory": [],
                 "2022-mapping": ["8.21"]
               }
             ]
              },
              {
                "element": "A.13.1.3",
                "title": "Segregation in networks",
                "type": "Subcategory",
                "description": "",
                "references": [
               {
                 "documentTitle": [],
                 "location": [],
                 "mandatory": [],
                 "2022-mapping": ["8.22"]
               }
             ]
              }
            ]
          },{
            "element": "A.13.2",
            "title": "Information transfer",
            "type": "Category",
            "description": "To maintain the security of information transferred within an organization and with any external entity.",
            "childElements": [
              {
                "element": "A.13.2.1",
                "title": "Information transfer policies and procedures",
                "type": "Subcategory",
                "description": "",
                "references": [
               {
                 "documentTitle": [],
                 "location": [],
                 "mandatory": [],
                 "2022-mapping": ["5.14"]
               }
             ]
              },
              {
                "element": "A.13.2.2",
                "title": "Agreements on information transfer",
                "type": "Subcategory",
                "description": "",
                "references": [
               {
                 "documentTitle": [],
                 "location": [],
                 "mandatory": [],
                 "2022-mapping": ["5.14"]
               }
             ]
              },
              {
                "element": "A.13.2.3",
                "title": "Electronic messaging",
                "type": "Subcategory",
                "description": "",
                "references": [
               {
                 "documentTitle": [],
                 "location": [],
                 "mandatory": [],
                 "2022-mapping": ["5.14"]
               }
             ]
              },
              {
                "element": "A.13.2.4",
                "title": "Confidentiality or nondisclosure agreements",
                "type": "Subcategory",
                "description": "",
                "references": [
               {
                 "documentTitle": [],
                 "location": [],
                 "mandatory": [],
                 "2022-mapping": ["6.6"]
               }
             ]
              }
            ]
          }
        ]
      },{
        "element": "A.14",
        "title": "System acquisition, development and maintenance",
        "type": "Function",
        "description": "",
        "childElements": [
          {
            "element": "A.14.1",
            "title": "Security requirements of information systems",
            "type": "Category",
            "description": "To ensure that information security is an integral part of information systems across the entire lifecycle. This also includes the requirements for information systems which provide services over public networks.",
            "childElements": [
              {
                "element": "A.14.1.1",
                "title": "Information security requirements analysis and specification",
                "type": "Subcategory",
                "description": "",
                "references": [
               {
                 "documentTitle": [],
                 "location": [],
                 "mandatory": [],
                 "2022-mapping": ["5.8"]
               }
             ]
              },
              {
                "element": "A.14.1.2",
                "title": "Securing application services on public networks",
                "type": "Subcategory",
                "description": "",
                "references": [
               {
                 "documentTitle": [],
                 "location": [],
                 "mandatory": [],
                 "2022-mapping": ["8.26"]
               }
             ]
              },
              {
                "element": "A.14.1.3",
                "title": "Protecting application services transactions",
                "type": "Subcategory",
                "description": "",
                "references": [
               {
                 "documentTitle": [],
                 "location": [],
                 "mandatory": [],
                 "2022-mapping": ["8.26"]
               }
             ]
              }
            ]
          },{
            "element": "A.14.2",
            "title": "Security in development and support processes",
            "type": "Category",
            "description": "To ensure that information security is designed and implemented within the development lifecycle of information systems.",
            "childElements": [
              {
                "element": "A.14.2.1",
                "title": "Secure development policy",
                "type": "Subcategory",
                "description": "",
                "references": [
               {
                 "documentTitle": [],
                 "location": [],
                 "mandatory": [],
                 "2022-mapping": ["8.25"]
               }
             ]
              },
              {
                "element": "A.14.2.2",
                "title": "System change control procedures",
                "type": "Subcategory",
                "description": "",
                "references": [
               {
                 "documentTitle": [],
                 "location": [],
                 "mandatory": [],
                 "2022-mapping": ["8.32"]
               }
             ]
              },
              {
                "element": "A.14.2.3",
                "title": "Technical review of applications after operating platform changes",
                "type": "Subcategory",
                "description": "",
                "references": [
               {
                 "documentTitle": [],
                 "location": [],
                 "mandatory": [],
                 "2022-mapping": ["8.32"]
               }
             ]
              },
              {
                "element": "A.14.2.4",
                "title": "Restrictions on changes to software packages",
                "type": "Subcategory",
                "description": "",
                "references": [
               {
                 "documentTitle": [],
                 "location": [],
                 "mandatory": [],
                 "2022-mapping": ["8.32"]
               }
             ]
              },
              {
                "element": "A.14.2.5",
                "title": "Secure system engineering principles",
                "type": "Subcategory",
                "description": "",
                "references": [
               {
                 "documentTitle": ["Secure system engineering principles"],
                 "location": [],
                 "mandatory": ["Y"],
                 "2022-mapping": ["8.27"]
               }
             ]
              },
              {
                "element": "A.14.2.6",
                "title": "Secure development environment",
                "type": "Subcategory",
                "description": "",
                "references": [
               {
                 "documentTitle": [],
                 "location": [],
                 "mandatory": [],
                 "2022-mapping": ["8.31"]
               }
             ]
              },
              {
                "element": "A.14.2.7",
                "title": "Outsourced development",
                "type": "Subcategory",
                "description": "",
                "references": [
               {
                 "documentTitle": [],
                 "location": [],
                 "mandatory": [],
                 "2022-mapping": ["8.30"]
               }
             ]
              },
              {
                "element": "A.14.2.8",
                "title": "System security testing",
                "type": "Subcategory",
                "description": "",
                "references": [
               {
                 "documentTitle": [],
                 "location": [],
                 "mandatory": [],
                 "2022-mapping": ["8.29"]
               }
             ]
              },
              {
                "element": "A.14.2.9",
                "title": "System acceptance testing",
                "type": "Subcategory",
                "description": "",
                "references": [
               {
                 "documentTitle": [],
                 "location": [],
                 "mandatory": [],
                 "2022-mapping": ["8.29"]
               }
             ]
              }
            ]
          },{
            "element": "A.14.3",
            "title": "Test data",
            "type": "Category",
            "description": "To ensure the protection of data used for testing.",
            "childElements": [
              {
                "element": "A.14.3.1",
                "title": "Protection of test data",
                "type": "Subcategory",
                "description": "",
                "references": [
               {
                 "documentTitle": [],
                 "location": [],
                 "mandatory": [],
                 "2022-mapping": ["8.33"]
               }
             ]
              }
            ]
          }
        ]
      },{
        "element": "A.15",
        "title": "Supplier relationships",
        "type": "Function",
        "description": "",
        "childElements": [
          {
            "element": "A.15.1",
            "title": "Information security in supplier relationships",
            "type": "Category",
            "description": "To ensure protection of the organization's assets that is accessible by suppliers",
            "childElements": [
              {
                "element": "A.15.1.1",
                "title": "Information security policy for supplier relationships",
                "type": "Subcategory",
                "description": "",
                "references": [
               {
                 "documentTitle": ["Supplier security policy"],
                 "location": [],
                 "mandatory": ["Y"],
                 "2022-mapping": ["5.19"]
               }
             ]
              },
              {
                "element": "A.15.1.2",
                "title": "Addressing security within supplier agreements",
                "type": "Subcategory",
                "description": "",
                "references": [
               {
                 "documentTitle": [],
                 "location": [],
                 "mandatory": [],
                 "2022-mapping": ["5.20"]
               }
             ]
              },
              {
                "element": "A.15.1.3",
                "title": "Information and communication technology supply chain",
                "type": "Subcategory",
                "description": "",
                "references": [
               {
                 "documentTitle": [],
                 "location": [],
                 "mandatory": [],
                 "2022-mapping": ["5.21"]
               }
             ]
              }
            ]
          },{
            "element": "A.15.2",
            "title": "Supplier service delivery management",
            "type": "Category",
            "description": "To maintain an agreed level of information security and service delivery in line with supplier agreements.",
            "childElements": [
              {
                "element": "A.15.2.1",
                "title": "Monitoring and review of supplier services",
                "type": "Subcategory",
                "description": "",
                "references": [
               {
                 "documentTitle": [],
                 "location": [],
                 "mandatory": [],
                 "2022-mapping": ["5.22"]
               }
             ]
              },
              {
                "element": "A.15.2.2",
                "title": "Managing changes to supplier services",
                "type": "Subcategory",
                "description": "",
                "references": [
               {
                 "documentTitle": [],
                 "location": [],
                 "mandatory": [],
                 "2022-mapping": ["5.22"]
               }
             ]
              }
            ]
          }
        ]
      },{
        "element": "A.16",
        "title": "Information security incident management",
        "type": "Function",
        "description": "",
        "childElements": [
          {
            "element": "A.16.1",
            "title": "Management of information security incidents and improvements",
            "type": "Category",
            "description": "To ensure a consistent and effective approach to the management of information security incidents, including communication on security events and weaknesses.",
            "childElements": [
              {
                "element": "A.16.1.1",
                "title": "Responsibilities and procedures",
                "type": "Subcategory",
                "description": "",
                "references": [
               {
                 "documentTitle": [],
                 "location": [],
                 "mandatory": [],
                 "2022-mapping": ["5.24"]
               }
             ]
              },
              {
                "element": "A.16.1.2",
                "title": "Reporting information security events",
                "type": "Subcategory",
                "description": "",
                "references": [
               {
                 "documentTitle": [],
                 "location": [],
                 "mandatory": [],
                 "2022-mapping": ["6.8"]
               }
             ]
              },
              {
                "element": "A.16.1.3",
                "title": "Reporting information security weaknesses",
                "type": "Subcategory",
                "description": "",
                "references": [
               {
                 "documentTitle": [],
                 "location": [],
                 "mandatory": [],
                 "2022-mapping": ["6.8"]
               }
             ]
              },
              {
                "element": "A.16.1.4",
                "title": "Assessment of and decision on information security events",
                "type": "Subcategory",
                "description": "",
                "references": [
               {
                 "documentTitle": [],
                 "location": [],
                 "mandatory": [],
                 "2022-mapping": ["5.25"]
               }
             ]
              },
              {
                "element": "A.16.1.5",
                "title": "Response to information security incidents",
                "type": "Subcategory",
                "description": "",
                "references": [
               {
                 "documentTitle": ["Incident management procedure"],
                 "location": [],
                 "mandatory": ["Y"],
                 "2022-mapping": ["5.26"]
               }
             ]
              },
              {
                "element": "A.16.1.6",
                "title": "Learning from information security incidents",
                "type": "Subcategory",
                "description": "",
                "references": [
               {
                 "documentTitle": [],
                 "location": [],
                 "mandatory": [],
                 "2022-mapping": ["5.27"]
               }
             ]
              },
              {
                "element": "A.16.1.7",
                "title": "Collection of evidence",
                "type": "Subcategory",
                "description": "",
                "references": [
               {
                 "documentTitle": [],
                 "location": [],
                 "mandatory": [],
                 "2022-mapping": ["5.28"]
               }
             ]
              }
            ]
          }
        ]
      },{
        "element": "A.17",
        "title": "Information security aspects of business continuity management",
        "type": "Function",
        "description": "",
        "childElements": [
          {
            "element": "A.17.1",
            "title": "Information security continuity",
            "type": "Category",
            "description": "Information security continuity shall be embedded in the organization's business continuity management systems.",
            "childElements": [
              {
                "element": "A.17.1.1",
                "title": "Planning information security continuity",
                "type": "Subcategory",
                "description": "",
                "references": [
               {
                 "documentTitle": [],
                 "location": [],
                 "mandatory": [],
                 "2022-mapping": ["5.29"]
               }
             ]
              },
              {
                "element": "A.17.1.2",
                "title": "Implementing information security continuity",
                "type": "Subcategory",
                "description": "",
                "references": [
               {
                 "documentTitle": ["Business continuity procedures"],
                 "location": [],
                 "mandatory": ["Y"],
                 "2022-mapping": ["5.29"]
               }
             ]
              },
              {
                "element": "A.17.1.3",
                "title": "Verify, review and evaluate information security continuity",
                "type": "Subcategory",
                "description": "",
                "references": [
               {
                 "documentTitle": [],
                 "location": [],
                 "mandatory": [],
                 "2022-mapping": ["5.29"]
               }
             ]
              }
            ]
          },{
              "element": "A.17.2",
              "title": "Redundancies",
              "type": "Category",
              "description": "To ensure availability of information processing facilities.",
              "childElements": [
                {
                  "element": "A.17.2.1",
                  "title": "Availability of information processing facilities",
                  "type": "Subcategory",
                  "description": "",
                  "references": [
                 {
                   "documentTitle": [],
                   "location": [],
                   "mandatory": [],
                   "2022-mapping": ["8.14"]
                 }
               ]
                }
              ]
          }
        ]
      },{
        "element": "A.18",
        "title": "Compliance",
        "type": "Function",
        "description": "",
        "childElements": [
          {
            "element": "A.18.1",
            "title": "Compliance with legal and contractual requirements",
            "type": "Category",
            "description": "To avoid breaches of legal, statutory, regulatory or contractual obligations related to information security and of any security requirements..",
            "childElements": [
              {
                "element": "A.18.1.1",
                "title": "Identification of applicable legislation and contractual requirements",
                "type": "Subcategory",
                "description": "",
                "references": [
               {
                 "documentTitle": ["Statutory, regulatory, and contractual requirements"],
                 "location": [],
                 "mandatory": ["Y"],
                 "2022-mapping": ["5.31"]
               }
             ]
              },
              {
                "element": "A.18.1.2",
                "title": "Intellectual property rights",
                "type": "Subcategory",
                "description": "",
                "references": [
               {
                 "documentTitle": [],
                 "location": [],
                 "mandatory": [],
                 "2022-mapping": ["5.32"]
               }
             ]
              },
              {
                "element": "A.18.1.3",
                "title": "Protection of records",
                "type": "Subcategory",
                "description": "",
                "references": [
               {
                 "documentTitle": [],
                 "location": [],
                 "mandatory": [],
                 "2022-mapping": ["5.33"]
               }
             ]
              },
              {
                "element": "A.18.1.4",
                "title": "Privacy and protection of personally identifiable information",
                "type": "Subcategory",
                "description": "",
                "references": [
               {
                 "documentTitle": [],
                 "location": [],
                 "mandatory": [],
                 "2022-mapping": ["5.34"]
               }
             ]
              },
              {
                "element": "A.18.1.5",
                "title": "Regulation of cryptographic controls",
                "type": "Subcategory",
                "description": "",
                "references": [
               {
                 "documentTitle": [],
                 "location": [],
                 "mandatory": [],
                 "2022-mapping": ["5.31"]
               }
             ]
              }
            ]
          },{
              "element": "A.18.2",
              "title": "Information security reviews",
              "type": "Category",
              "description": "To ensure that information security is implemented and operated in accordance with the organizational policies and procedures.",
              "childElements": [
                {
                  "element": "A.18.2.1",
                  "title": "Independent review of information security",
                  "type": "Subcategory",
                  "description": "",
                  "references": [
                 {
                   "documentTitle": [],
                   "location": [],
                   "mandatory": [],
                   "2022-mapping": ["5.35"]
                 }
               ]
                },
                {
                  "element": "A.18.2.2",
                  "title": "Compliance with security policies and standards",
                  "type": "Subcategory",
                  "description": "",
                  "references": [
                 {
                   "documentTitle": [],
                   "location": [],
                   "mandatory": [],
                   "2022-mapping": ["5.36"]
                 }
               ]
                },
                {
                  "element": "A.18.2.3",
                  "title": "Technical compliance review",
                  "type": "Subcategory",
                  "description": "",
                  "references": [
                 {
                   "documentTitle": [],
                   "location": [],
                   "mandatory": [],
                   "2022-mapping": ["5.36"]
                 }
               ]
                }
              ]
          }
        ]
      }
    ]
}